odoo/addons/base_dns_infrastructure/README.rst
odoo/addons/base_dns_infrastructure/__init__.py
odoo/addons/base_dns_infrastructure/__manifest__.py
odoo/addons/base_dns_infrastructure/data/dns_record_type.xml
odoo/addons/base_dns_infrastructure/demo/base_dns_infrastructure.xml
odoo/addons/base_dns_infrastructure/i18n/base_dns_infrastructure.pot
odoo/addons/base_dns_infrastructure/i18n/it.po
odoo/addons/base_dns_infrastructure/models/__init__.py
odoo/addons/base_dns_infrastructure/models/dns_domain_zone/__init__.py
odoo/addons/base_dns_infrastructure/models/dns_domain_zone/common.py
odoo/addons/base_dns_infrastructure/models/dns_record/__init__.py
odoo/addons/base_dns_infrastructure/models/dns_record/common.py
odoo/addons/base_dns_infrastructure/models/dns_record_type/__init__.py
odoo/addons/base_dns_infrastructure/models/dns_record_type/common.py
odoo/addons/base_dns_infrastructure/models/res_partner/__init__.py
odoo/addons/base_dns_infrastructure/models/res_partner/common.py
odoo/addons/base_dns_infrastructure/readme/CONFIGURE.md
odoo/addons/base_dns_infrastructure/readme/CONTRIBUTORS.md
odoo/addons/base_dns_infrastructure/readme/CREDITS.md
odoo/addons/base_dns_infrastructure/readme/DESCRIPTION.md
odoo/addons/base_dns_infrastructure/readme/INSTALL.md
odoo/addons/base_dns_infrastructure/readme/USAGE.md
odoo/addons/base_dns_infrastructure/security/dns.xml
odoo/addons/base_dns_infrastructure/security/ir.model.access.csv
odoo/addons/base_dns_infrastructure/static/description/icon.png
odoo/addons/base_dns_infrastructure/static/description/index.html
odoo/addons/base_dns_infrastructure/static/src/img/network.png
odoo/addons/base_dns_infrastructure/views/dns_domain_zone.xml
odoo/addons/base_dns_infrastructure/views/dns_menu.xml
odoo/addons/base_dns_infrastructure/views/dns_record.xml
odoo/addons/base_dns_infrastructure/views/dns_record_type.xml
odoo_addon_base_dns_infrastructure-18.0.1.0.0.5.dist-info/METADATA
odoo_addon_base_dns_infrastructure-18.0.1.0.0.5.dist-info/WHEEL
odoo_addon_base_dns_infrastructure-18.0.1.0.0.5.dist-info/top_level.txt
odoo_addon_base_dns_infrastructure-18.0.1.0.0.5.dist-info/RECORD
