Metadata-Version: 2.1
Name: odoo-addon-base_dns_infrastructure
Version: 18.0.1.0.0.5
Requires-Python: >=3.10
Requires-Dist: odoo==18.0.*
Requires-Dist: validator-collection
Summary: Base module for DNS infrastructure
Home-page: https://github.com/OCA/infrastructure
License: AGPL-3
Author: Elico Corp, LasLabs, Mind And Go, Odoo Community Association (OCA)
Author-email: support@odoo-community.org
Classifier: Programming Language :: Python
Classifier: Framework :: Odoo
Classifier: Framework :: Odoo :: 18.0
Classifier: License :: OSI Approved :: GNU Affero General Public License v3
